encrypted_cookiejar/__init__.py
encrypted_cookiejar-1.0.0.dist-info/LICENSE
encrypted_cookiejar-1.0.0.dist-info/METADATA
encrypted_cookiejar-1.0.0.dist-info/WHEEL
encrypted_cookiejar-1.0.0.dist-info/top_level.txt
encrypted_cookiejar-1.0.0.dist-info/zip-safe
encrypted_cookiejar-1.0.0.dist-info/RECORD
